LLMOrchestrator/__init__.py
LLMOrchestrator/controller.py
LLMOrchestrator/generator.py
LLMOrchestrator/models.py
LLMOrchestrator/orchestration_manager.py
LLMOrchestrator/task_engine.py
LLMOrchestrator/verifier.py
LLMOrchestrator/examples/__init__.py
LLMOrchestrator/examples/adaptive_learning.py
LLMOrchestrator/examples/basic_usage.py
LLMOrchestrator/examples/custom_controller.py
LLMOrchestrator/examples/local_model_example.py
LLMOrchestrator/examples/mock_llm.py
LLMOrchestrator/examples/openai_example.py
LLMOrchestrator/examples/parallel_processing.py
LLMOrchestrator/models/__init__.py
LLMOrchestrator/models/base_model.py
LLMOrchestrator/models/local_model.py
LLMOrchestrator/models/openai_model.py
LLMOrchestrator/tests/__init__.py
LLMOrchestrator/tests/conftest.py
LLMOrchestrator/tests/test_controller.py
llmorchestrator-0.1.0.dist-info/licenses/LICENSE
tests/__init__.py
tests/test_controller.py
llmorchestrator-0.1.0.dist-info/METADATA
llmorchestrator-0.1.0.dist-info/WHEEL
llmorchestrator-0.1.0.dist-info/top_level.txt
llmorchestrator-0.1.0.dist-info/RECORD
