Metadata-Version: 2.4
Name: LLMOrchestrator
Version: 0.1.0
Summary: A framework for orchestrating and managing Large Language Model operations
Home-page: https://github.com/builtbypyro/LLMOrchestrator
Author: Trisanth Srinivasan
Author-email: contact@cyrionlabs.org
Classifier: Development Status :: 3 - Alpha
Classifier: Intended Audience :: Developers
Classifier: License :: OSI Approved :: MIT License
Classifier: Programming Language :: Python :: 3
Classifier: Programming Language :: Python :: 3.8
Classifier: Programming Language :: Python :: 3.9
Classifier: Programming Language :: Python :: 3.10
Classifier: Programming Language :: Python :: 3.11
Requires-Python: >=3.8
License-File: LICENSE
Requires-Dist: openai>=1.0.0
Requires-Dist: python-dotenv>=0.19.0
Requires-Dist: torch>=2.0.0
Requires-Dist: transformers>=4.30.0
Requires-Dist: accelerate>=0.20.0
Requires-Dist: numpy>=1.21.0
Requires-Dist: scikit-learn>=1.0.0
Requires-Dist: tqdm>=4.65.0
Requires-Dist: pydantic>=2.0.0
Requires-Dist: tenacity>=8.0.0
Requires-Dist: cachetools>=5.0.0
Requires-Dist: prompt_toolkit>=3.0.0
Requires-Dist: rich>=10.0.0
Requires-Dist: pytest>=7.0.0
Requires-Dist: pytest-cov>=4.0.0
Requires-Dist: pytest-mock>=3.10.0
Dynamic: author
Dynamic: author-email
Dynamic: classifier
Dynamic: description
Dynamic: description-content-type
Dynamic: home-page
Dynamic: license-file
Dynamic: requires-dist
Dynamic: requires-python
Dynamic: summary
